aimluae/__init__.py
aimluae/datasets.py
aimluae-1.0.22.dist-info/LICENCE.txt
aimluae-1.0.22.dist-info/METADATA
aimluae-1.0.22.dist-info/WHEEL
aimluae-1.0.22.dist-info/top_level.txt
aimluae-1.0.22.dist-info/RECORD
