Metadata-Version: 2.1
Name: aimluae
Version: 1.0.22
Summary: Artificial Intelligence & Machine Learning UAE
Home-page: 
Author: Salman Khan
Author-email: maker57sk@gmail.com
License: MIT
Platform: UNKNOWN
Classifier: Development Status :: 5 - Production/Stable
Classifier: Intended Audience :: Education
Classifier: Operating System :: Microsoft :: Windows :: Windows 10
Classifier: License :: OSI Approved :: MIT License
Classifier: Programming Language :: Python :: 3
License-File: LICENCE.txt
